MANIFEST.in
README.md
setup.py
radial_distance_layout/__init__.py
radial_distance_layout.egg-info/PKG-INFO
radial_distance_layout.egg-info/SOURCES.txt
radial_distance_layout.egg-info/dependency_links.txt
radial_distance_layout.egg-info/not-zip-safe
radial_distance_layout.egg-info/requires.txt
radial_distance_layout.egg-info/top_level.txt