Metadata-Version: 1.0
Name: radial-distance-layout
Version: 0.1
Summary: Generates a radial layout for trees whose nodes are associated with a distance to the root.
Home-page: https://bitbucket.org/bfmaier/radial-distance-layout
Author: Benjamin F. Maier
Author-email: bfmaier@physik.hu-berlin.de
License: MIT
Platform: UNKNOWN
